<?xml version='1.0' encoding='UTF-8'?><moduledata><entity tablename='Ent' formatname='faleconosco'><SigaFiles Text='SQG'><Dados><attribute domainname='nome'><![CDATA[DAN EL PIERRE REZENDE]]></attribute><attribute domainname='sexo'><![CDATA[masculino]]></attribute><attribute domainname='nascimento'><![CDATA[20091989]]></attribute><attribute domainname='estadocivil'><![CDATA[Casado(a)]]></attribute><attribute domainname='cpf'><![CDATA[025232751-98]]></attribute><attribute domainname='celular'><![CDATA[(62) 99933-3333]]></attribute><attribute domainname='telefone'><![CDATA[(62) 3551-8116]]></attribute><attribute domainname='email'><![CDATA[DAN.REZENDE@PIRACANJUBA.COM.BR]]></attribute><attribute domainname='cep'><![CDATA[75240000]]></attribute><attribute domainname='endereco'><![CDATA[RODOVIA GO 020]]></attribute><attribute domainname='numero'><![CDATA[KM 46]]></attribute><attribute domainname='complemento'><![CDATA[FABRICA]]></attribute><attribute domainname='pais'><![CDATA[BR]]></attribute><attribute domainname='estado'><![CDATA[9]]></attribute><attribute domainname='cidade'><![CDATA[523]]></attribute><attribute domainname='mensagem'><![CDATA[TESTE DE FORMULRIO.]]></attribute><attribute domainname='autorizacao'><![CDATA[N]]></attribute></Dados></SigaFiles></entity></moduledata>