{"CNT_ID":"389","CNT_SIT":"1","CNT_IPR":"8","CNT_TIP":"NT","CNT_DTA":"2016-07-22 17:40:26","CNT_TIS":"","CNT_TIT":"O que \u00e9 alergia alimentar?","CNT_OLH":"","CNT_TXT":"<p>A alergia &eacute; caracterizada quando uma pessoa apresenta uma rea&ccedil;&atilde;o adversa ap&oacute;s a ingest&atilde;o de um determinado alimento ou aditivos alimentares. As rea&ccedil;&otilde;es podem variar desde o surgimento de sintomas na pele, no sistema gastrointestinal e respirat&oacute;rio, at&eacute; casos mais graves, quando podem comprometer v&aacute;rios &oacute;rg&atilde;os ocasionando uma rea&ccedil;&atilde;o anafil&aacute;tica. J&aacute; a intoler&acirc;ncia alimentar &eacute; a resposta exagerada do organismo devido a produ&ccedil;&atilde;o insuficiente ou ausente no organismo de enzimas digestivas. Toda subst&acirc;ncia capaz de desencadear uma rea&ccedil;&atilde;o de hipersensibilidade &eacute; considerada al&eacute;rgena.<\/p>","CNT_RES":"","CNT_FT1":"","CNT_FT1_":"","CNT_RDT":"","CNT_EMA":"","CNT_CHV":"","CNT_CMT":"0","CNT_CMD":"","CNT_CKY":"500","CNT_TAG":"","CNT_CAT":"","CNT_ENQ":"0","CNT_CTT":"","CNT_PAI":"","CNT_EST":"","CNT_STS":"1","CNT_EMB":"","CNT_EMB2":"","CNT_LOC":"","CNT_VOT":"0","CNT_NOT":"0","URL":"http:\/\/www.piracanjuba.com.br\/{news_url}\/2016\/07\/22\/o-que-e-alergia-alimentar-389.html","totComments":"0","comments":[]}